dicta_onnx/__init__.py
dicta_onnx/model.py
dicta_onnx-1.0.9.dist-info/METADATA
dicta_onnx-1.0.9.dist-info/WHEEL
dicta_onnx-1.0.9.dist-info/RECORD
