Metadata-Version: 2.4
Name: dicta-onnx
Version: 1.0.9
Summary: Add diacritics to Hebrew text using Dicta model
Project-URL: Homepage, https://github.com/thewh1teagle/dicta-onnx
Project-URL: Repository, https://github.com/thewh1teagle/dicta-onnx
Project-URL: Issues, https://github.com/thewh1teagle/dicta-onnx/issues
Author-email: thewh1teagle <61390950+thewh1teagle@users.noreply.github.com>
Requires-Python: >=3.11
Requires-Dist: onnxruntime==1.21.1
Requires-Dist: tokenizers>=0.21.1
